{"name": "Oberembrach", "bfs": 65, "agedistribution": [{"age": 0, "count": 10.0, "yeartorepresentative": 38.0}, {"age": 1, "count": 13.0, "yeartorepresentative": 37.0}, {"age": 2, "count": 12.0, "yeartorepresentative": 36.0}, {"age": 3, "count": 14.0, "yeartorepresentative": 35.0}, {"age": 4, "count": 13.0, "yeartorepresentative": 34.0}, {"age": 5, "count": 6.0, "yeartorepresentative": 33.0}, {"age": 6, "count": 12.0, "yeartorepresentative": 32.0}, {"age": 7, "count": 14.0, "yeartorepresentative": 31.0}, {"age": 8, "count": 5.0, "yeartorepresentative": 30.0}, {"age": 9, "count": 9.0, "yeartorepresentative": 29.0}, {"age": 10, "count": 7.0, "yeartorepresentative": 28.0}, {"age": 11, "count": 7.0, "yeartorepresentative": 27.0}, {"age": 12, "count": 13.0, "yeartorepresentative": 26.0}, {"age": 13, "count": 5.0, "yeartorepresentative": 25.0}, {"age": 14, "count": 8.0, "yeartorepresentative": 24.0}, {"age": 15, "count": 11.0, "yeartorepresentative": 23.0}, {"age": 16, "count": 13.0, "yeartorepresentative": 22.0}, {"age": 17, "count": 9.0, "yeartorepresentative": 21.0}, {"age": 18, "count": 8.0, "yeartorepresentative": 20.0}, {"age": 19, "count": 9.0, "yeartorepresentative": 19.0}, {"age": 20, "count": 9.0, "yeartorepresentative": 18.0}, {"age": 21, "count": 6.0, "yeartorepresentative": 17.0}, {"age": 22, "count": 10.0, "yeartorepresentative": 16.0}, {"age": 23, "count": 16.0, "yeartorepresentative": 15.0}, {"age": 24, "count": 10.0, "yeartorepresentative": 14.0}, {"age": 25, "count": 7.0, "yeartorepresentative": 13.0}, {"age": 26, "count": 3.0, "yeartorepresentative": 12.0}, {"age": 27, "count": 11.0, "yeartorepresentative": 11.0}, {"age": 28, "count": 10.0, "yeartorepresentative": 10.0}, {"age": 29, "count": 7.0, "yeartorepresentative": 9.0}, {"age": 30, "count": 14.0, "yeartorepresentative": 8.0}, {"age": 31, "count": 12.0, "yeartorepresentative": 7.0}, {"age": 32, "count": 13.0, "yeartorepresentative": 6.0}, {"age": 33, "count": 4.0, "yeartorepresentative": 5.0}, {"age": 34, "count": 12.0, "yeartorepresentative": 4.0}, {"age": 35, "count": 17.0, "yeartorepresentative": 3.0}, {"age": 36, "count": 11.0, "yeartorepresentative": 2.0}, {"age": 37, "count": 11.0, "yeartorepresentative": 1.0}, {"age": 38, "count": 15.0, "yeartorepresentative": 0.0}, {"age": 39, "count": 25.0, "yeartorepresentative": 1.0}, {"age": 40, "count": 16.0, "yeartorepresentative": 2.0}, {"age": 41, "count": 23.0, "yeartorepresentative": 3.0}, {"age": 42, "count": 13.0, "yeartorepresentative": 4.0}, {"age": 43, "count": 13.0, "yeartorepresentative": 3.0}, {"age": 44, "count": 15.0, "yeartorepresentative": 2.0}, {"age": 45, "count": 15.0, "yeartorepresentative": 1.0}, {"age": 46, "count": 19.0, "yeartorepresentative": 0.0}, {"age": 47, "count": 13.0, "yeartorepresentative": 1.0}, {"age": 48, "count": 18.0, "yeartorepresentative": 0.0}, {"age": 49, "count": 22.0, "yeartorepresentative": 1.0}, {"age": 50, "count": 16.0, "yeartorepresentative": 2.0}, {"age": 51, "count": 22.0, "yeartorepresentative": 2.0}, {"age": 52, "count": 27.0, "yeartorepresentative": 1.0}, {"age": 53, "count": 26.0, "yeartorepresentative": 0.0}, {"age": 54, "count": 29.0, "yeartorepresentative": 1.0}, {"age": 55, "count": 22.0, "yeartorepresentative": 2.0}, {"age": 56, "count": 20.0, "yeartorepresentative": 3.0}, {"age": 57, "count": 24.0, "yeartorepresentative": 3.0}, {"age": 58, "count": 21.0, "yeartorepresentative": 2.0}, {"age": 59, "count": 14.0, "yeartorepresentative": 1.0}, {"age": 60, "count": 20.0, "yeartorepresentative": 0.0}, {"age": 61, "count": 14.0, "yeartorepresentative": 1.0}, {"age": 62, "count": 9.0, "yeartorepresentative": 2.0}, {"age": 63, "count": 16.0, "yeartorepresentative": 3.0}, {"age": 64, "count": 7.0, "yeartorepresentative": 4.0}, {"age": 65, "count": 19.0, "yeartorepresentative": 5.0}, {"age": 66, "count": 17.0, "yeartorepresentative": 6.0}, {"age": 67, "count": 10.0, "yeartorepresentative": 7.0}, {"age": 68, "count": 13.0, "yeartorepresentative": 8.0}, {"age": 69, "count": 17.0, "yeartorepresentative": 9.0}, {"age": 70, "count": 14.0, "yeartorepresentative": 10.0}, {"age": 71, "count": 11.0, "yeartorepresentative": 11.0}, {"age": 72, "count": 4.0, "yeartorepresentative": 12.0}, {"age": 73, "count": 11.0, "yeartorepresentative": 13.0}, {"age": 74, "count": 6.0, "yeartorepresentative": 14.0}, {"age": 75, "count": 11.0, "yeartorepresentative": 15.0}, {"age": 76, "count": 11.0, "yeartorepresentative": 16.0}, {"age": 77, "count": 5.0, "yeartorepresentative": 17.0}, {"age": 78, "count": 12.0, "yeartorepresentative": 18.0}, {"age": 79, "count": 11.0, "yeartorepresentative": 19.0}, {"age": 80, "count": 7.0, "yeartorepresentative": 20.0}, {"age": 81, "count": 6.0, "yeartorepresentative": 21.0}, {"age": 82, "count": 6.0, "yeartorepresentative": 22.0}, {"age": 83, "count": 4.0, "yeartorepresentative": 23.0}, {"age": 84, "count": 2.0, "yeartorepresentative": 24.0}, {"age": 85, "count": 5.0, "yeartorepresentative": 25.0}, {"age": 86, "count": 5.0, "yeartorepresentative": 26.0}, {"age": 87, "count": 2.0, "yeartorepresentative": 27.0}, {"age": 88, "count": 3.0, "yeartorepresentative": 28.0}, {"age": 89, "count": 0.0, "yeartorepresentative": 29.0}, {"age": 90, "count": 3.0, "yeartorepresentative": 30.0}, {"age": 91, "count": 4.0, "yeartorepresentative": 31.0}, {"age": 92, "count": 1.0, "yeartorepresentative": 32.0}, {"age": 93, "count": 1.0, "yeartorepresentative": 33.0}, {"age": 94, "count": 0.0, "yeartorepresentative": 34.0}, {"age": 95, "count": 0.0, "yeartorepresentative": 35.0}, {"age": 96, "count": 0.0, "yeartorepresentative": 36.0}, {"age": 97, "count": 0.0, "yeartorepresentative": 37.0}, {"age": 98, "count": 1.0, "yeartorepresentative": 38.0}], "agegroups": {"0": {"inhabitants": 0.0, "executives": 0}, "18-39": {"inhabitants": 26.0, "executives": 20}, "40-64": {"inhabitants": 50.0, "executives": 80}, "65-79": {"inhabitants": 19.0, "executives": 0}, ">80": {"inhabitants": 5.0, "executives": 0}}, "executives": [{"id": 381, "name": "Michael Gerschwyler", "agegroup": 1983, "agecalculated": 38.0, "party": "parteilos", "sex": "m"}, {"id": 382, "name": "Frank Meyenberg", "agegroup": 1975, "agecalculated": 46.0, "party": "parteilos", "sex": "m"}, {"id": 384, "name": "Martin Widmer", "agegroup": 1973, "agecalculated": 48.0, "party": "glp", "sex": "m"}, {"id": 383, "name": "Michael Welz", "agegroup": 1968, "agecalculated": 53.0, "party": "EDU", "sex": "m"}, {"id": 380, "name": "Verena Koch Hanselmann", "agegroup": 1961, "agecalculated": 60.0, "party": "parteilos", "sex": "w"}], "gender": {"m": 49, "w": 51}, "representativeages": [{"age": 60, "ids": [380]}, {"age": 53, "ids": [383]}, {"age": 48, "ids": [384]}, {"age": 46, "ids": [382]}, {"age": 38, "ids": [381]}], "party": {"parteilos": {"2019": 0, "board": 60.0}, "svp": {"2019": 46, "board": 0.0}, "glp": {"2019": 8, "board": 20.0}, "fdp": {"2019": 12, "board": 0.0}, "edu": {"2019": 9, "board": 20.0}, "sp": {"2019": 10, "board": 0.0}, "gr\u00fcne": {"2019": 6, "board": 0.0}}, "executiveparty": {"is": ["parteilos", "parteilos", "parteilos", "edu", "glp"], "should": ["svp", "svp", "svp", "svp", "fdp"]}, "hasages": true, "ageperexecutive": true}