{"name": "Winkel", "type": "gemeinderat", "bfs": 72, "agedistribution": [{"age": 0, "count": 52.0, "yeartorepresentative": 49.0}, {"age": 1, "count": 41.0, "yeartorepresentative": 48.0}, {"age": 2, "count": 53.0, "yeartorepresentative": 47.0}, {"age": 3, "count": 46.0, "yeartorepresentative": 46.0}, {"age": 4, "count": 39.0, "yeartorepresentative": 45.0}, {"age": 5, "count": 46.0, "yeartorepresentative": 44.0}, {"age": 6, "count": 57.0, "yeartorepresentative": 43.0}, {"age": 7, "count": 48.0, "yeartorepresentative": 42.0}, {"age": 8, "count": 54.0, "yeartorepresentative": 41.0}, {"age": 9, "count": 39.0, "yeartorepresentative": 40.0}, {"age": 10, "count": 40.0, "yeartorepresentative": 39.0}, {"age": 11, "count": 44.0, "yeartorepresentative": 38.0}, {"age": 12, "count": 30.0, "yeartorepresentative": 37.0}, {"age": 13, "count": 36.0, "yeartorepresentative": 36.0}, {"age": 14, "count": 31.0, "yeartorepresentative": 35.0}, {"age": 15, "count": 24.0, "yeartorepresentative": 34.0}, {"age": 16, "count": 35.0, "yeartorepresentative": 33.0}, {"age": 17, "count": 28.0, "yeartorepresentative": 32.0}, {"age": 18, "count": 42.0, "yeartorepresentative": 31.0}, {"age": 19, "count": 40.0, "yeartorepresentative": 30.0}, {"age": 20, "count": 51.0, "yeartorepresentative": 29.0}, {"age": 21, "count": 46.0, "yeartorepresentative": 28.0}, {"age": 22, "count": 49.0, "yeartorepresentative": 27.0}, {"age": 23, "count": 37.0, "yeartorepresentative": 26.0}, {"age": 24, "count": 45.0, "yeartorepresentative": 25.0}, {"age": 25, "count": 42.0, "yeartorepresentative": 24.0}, {"age": 26, "count": 46.0, "yeartorepresentative": 23.0}, {"age": 27, "count": 38.0, "yeartorepresentative": 22.0}, {"age": 28, "count": 43.0, "yeartorepresentative": 21.0}, {"age": 29, "count": 55.0, "yeartorepresentative": 20.0}, {"age": 30, "count": 47.0, "yeartorepresentative": 19.0}, {"age": 31, "count": 46.0, "yeartorepresentative": 18.0}, {"age": 32, "count": 64.0, "yeartorepresentative": 17.0}, {"age": 33, "count": 46.0, "yeartorepresentative": 16.0}, {"age": 34, "count": 50.0, "yeartorepresentative": 15.0}, {"age": 35, "count": 67.0, "yeartorepresentative": 14.0}, {"age": 36, "count": 59.0, "yeartorepresentative": 13.0}, {"age": 37, "count": 49.0, "yeartorepresentative": 12.0}, {"age": 38, "count": 67.0, "yeartorepresentative": 11.0}, {"age": 39, "count": 79.0, "yeartorepresentative": 10.0}, {"age": 40, "count": 63.0, "yeartorepresentative": 9.0}, {"age": 41, "count": 82.0, "yeartorepresentative": 8.0}, {"age": 42, "count": 61.0, "yeartorepresentative": 7.0}, {"age": 43, "count": 69.0, "yeartorepresentative": 6.0}, {"age": 44, "count": 81.0, "yeartorepresentative": 5.0}, {"age": 45, "count": 73.0, "yeartorepresentative": 4.0}, {"age": 46, "count": 70.0, "yeartorepresentative": 3.0}, {"age": 47, "count": 77.0, "yeartorepresentative": 2.0}, {"age": 48, "count": 87.0, "yeartorepresentative": 1.0}, {"age": 49, "count": 75.0, "yeartorepresentative": 0.0}, {"age": 50, "count": 72.0, "yeartorepresentative": 0.0}, {"age": 51, "count": 83.0, "yeartorepresentative": 1.0}, {"age": 52, "count": 72.0, "yeartorepresentative": 2.0}, {"age": 53, "count": 78.0, "yeartorepresentative": 3.0}, {"age": 54, "count": 98.0, "yeartorepresentative": 2.0}, {"age": 55, "count": 82.0, "yeartorepresentative": 1.0}, {"age": 56, "count": 94.0, "yeartorepresentative": 0.0}, {"age": 57, "count": 65.0, "yeartorepresentative": 1.0}, {"age": 58, "count": 91.0, "yeartorepresentative": 2.0}, {"age": 59, "count": 81.0, "yeartorepresentative": 2.0}, {"age": 60, "count": 67.0, "yeartorepresentative": 1.0}, {"age": 61, "count": 80.0, "yeartorepresentative": 0.0}, {"age": 62, "count": 70.0, "yeartorepresentative": 1.0}, {"age": 63, "count": 69.0, "yeartorepresentative": 0.0}, {"age": 64, "count": 60.0, "yeartorepresentative": 1.0}, {"age": 65, "count": 46.0, "yeartorepresentative": 2.0}, {"age": 66, "count": 55.0, "yeartorepresentative": 3.0}, {"age": 67, "count": 53.0, "yeartorepresentative": 4.0}, {"age": 68, "count": 47.0, "yeartorepresentative": 5.0}, {"age": 69, "count": 46.0, "yeartorepresentative": 6.0}, {"age": 70, "count": 45.0, "yeartorepresentative": 7.0}, {"age": 71, "count": 50.0, "yeartorepresentative": 8.0}, {"age": 72, "count": 62.0, "yeartorepresentative": 9.0}, {"age": 73, "count": 36.0, "yeartorepresentative": 10.0}, {"age": 74, "count": 47.0, "yeartorepresentative": 11.0}, {"age": 75, "count": 41.0, "yeartorepresentative": 12.0}, {"age": 76, "count": 41.0, "yeartorepresentative": 13.0}, {"age": 77, "count": 37.0, "yeartorepresentative": 14.0}, {"age": 78, "count": 45.0, "yeartorepresentative": 15.0}, {"age": 79, "count": 32.0, "yeartorepresentative": 16.0}, {"age": 80, "count": 33.0, "yeartorepresentative": 17.0}, {"age": 81, "count": 23.0, "yeartorepresentative": 18.0}, {"age": 82, "count": 27.0, "yeartorepresentative": 19.0}, {"age": 83, "count": 25.0, "yeartorepresentative": 20.0}, {"age": 84, "count": 19.0, "yeartorepresentative": 21.0}, {"age": 85, "count": 15.0, "yeartorepresentative": 22.0}, {"age": 86, "count": 18.0, "yeartorepresentative": 23.0}, {"age": 87, "count": 11.0, "yeartorepresentative": 24.0}, {"age": 88, "count": 9.0, "yeartorepresentative": 25.0}, {"age": 89, "count": 12.0, "yeartorepresentative": 26.0}, {"age": 90, "count": 6.0, "yeartorepresentative": 27.0}, {"age": 91, "count": 6.0, "yeartorepresentative": 28.0}, {"age": 92, "count": 3.0, "yeartorepresentative": 29.0}, {"age": 93, "count": 2.0, "yeartorepresentative": 30.0}, {"age": 94, "count": 1.0, "yeartorepresentative": 31.0}, {"age": 95, "count": 3.0, "yeartorepresentative": 32.0}, {"age": 96, "count": 1.0, "yeartorepresentative": 33.0}, {"age": 97, "count": 0.0, "yeartorepresentative": 34.0}, {"age": 98, "count": 0.0, "yeartorepresentative": 35.0}, {"age": 99, "count": 0.0, "yeartorepresentative": 36.0}, {"age": 100, "count": 1.0, "yeartorepresentative": 37.0}], "agegroups": {"0": {"inhabitants": 0.0, "executives": 0}, "18-39": {"inhabitants": 28.0, "executives": 0}, "40-64": {"inhabitants": 49.0, "executives": 100}, "65-79": {"inhabitants": 17.0, "executives": 0}, ">80": {"inhabitants": 6.0, "executives": 0}}, "executives": [{"id": 152, "name": "Dominik B\u00e4nninger", "agegroup": 1972, "agecalculated": 49.0, "party": "SVP", "sex": "m"}, {"id": 151, "name": "Marcel N\u00f6tzli", "agegroup": 1971, "agecalculated": 50.0, "party": "SVP", "sex": "m"}, {"id": 153, "name": "Mariano De Palatis", "agegroup": 1965, "agecalculated": 56.0, "party": "SVP", "sex": "m"}, {"id": 155, "name": "Reto Huber", "agegroup": 1960, "agecalculated": 61.0, "party": "SVP", "sex": "m"}, {"id": 154, "name": "Christian Erzinger", "agegroup": 1958, "agecalculated": 63.0, "party": "FDP", "sex": "m"}], "gender": {"m": 50, "w": 50}, "representativeages": [{"age": 63, "ids": [154]}, {"age": 61, "ids": [155]}, {"age": 56, "ids": [153]}, {"age": 50, "ids": [151]}, {"age": 49, "ids": [152]}], "party": {"svp": {"2019": 39, "board": 80.0}, "glp": {"2019": 10, "board": 0.0}, "sp": {"2019": 8, "board": 0.0}, "gr\u00fcne": {"2019": 6, "board": 0.0}, "fdp": {"2019": 25, "board": 20.0}}, "executiveparty": {"is": ["svp", "svp", "svp", "svp", "fdp"], "should": ["svp", "svp", "svp", "fdp", "fdp"]}, "hasages": true, "ageperexecutive": true}